megaopen/__init__.py
megaopen/model_api/__init__.py
megaopen/model_api/api.py
megaopen/model_api/mega_params.py
megaopen/model_api/params.py
megaopen/utils/__init__.py
megaopen/utils/http_client.py
megaopen/utils/jwt_token.py
megaopen/utils/sse_client.py
megatechai/__init__.py
megatechai/model_api/__init__.py
megatechai/model_api/api.py
megatechai/model_api/mega_params.py
megatechai/model_api/params.py
megatechai/utils/__init__.py
megatechai/utils/http_client.py
megatechai/utils/jwt_token.py
megatechai/utils/sse_client.py
megaopen-1.0.0.dist-info/LICENSE
megaopen-1.0.0.dist-info/METADATA
megaopen-1.0.0.dist-info/WHEEL
megaopen-1.0.0.dist-info/top_level.txt
megaopen-1.0.0.dist-info/RECORD
